easyimage/__init__.py
easyimage-0.0.1.dist-info/METADATA
easyimage-0.0.1.dist-info/WHEEL
easyimage-0.0.1.dist-info/top_level.txt
easyimage-0.0.1.dist-info/RECORD
